{
    "thread": {
        "uuid": "5e819ae697d05e1a4f29200a2ce6b5a11fdf0c49",
        "url": "https://trentonubgm295284.pages10.com/solar-power-packages-for-home-create-electrical-power-and-save-money-59779646",
        "site_full": "trentonubgm295284.pages10.com",
        "site": "pages10.com",
        "site_section": "https://pages10.com/rss-homepage.php?1",
        "site_categories": [],
        "section_title": "pages10.com RSS feed",
        "title": "Solar Power Packages For Home - Create Electrical Power And Save Money",
        "title_full": "Solar Power Packages For Home - Create Electrical Power And Save Money",
        "published": "2023-12-28T22:01:00.000+02:00",
        "replies_count": 0,
        "participants_count": 1,
        "site_type": "news",
        "country": "IN",
        "main_image": "",
        "performance_score": 0,
        "domain_rank": 6184,
        "domain_rank_updated": "2023-12-26T12:06:20.000+02:00",
        "reach": null,
        "social": {
            "facebook": {
                "likes": 0,
                "comments": 0,
                "shares": 0
            },
            "gplus": {
                "shares": 0
            },
            "pinterest": {
                "shares": 0
            },
            "linkedin": {
                "shares": 0
            },
            "stumbledupon": {
                "shares": 0
            },
            "vk": {
                "shares": 0
            }
        }
    },
    "uuid": "5e819ae697d05e1a4f29200a2ce6b5a11fdf0c49",
    "url": "https://trentonubgm295284.pages10.com/solar-power-packages-for-home-create-electrical-power-and-save-money-59779646",
    "ord_in_thread": 0,
    "parent_url": null,
    "author": "Trentonubgm",
    "published": "2023-12-28T22:01:00.000+02:00",
    "title": "Solar Power Packages For Home - Create Electrical Power And Save Money",
    "text": "Sustainable energy is our only possibility. That might sound severe, however it's the fact. If we continue to depend on oil and other present types of energy production, there will be serious consequences. While there are lots of reasons for our gashouse emission problems, oil is the number one culprit. And why do we continue to utilize oil? Revenues. If we don't alter, our own greed will cause our death. That's fantastic to think about. The dinosaurs were supposedly extinct by a meteor; they had no chance. Do you think they would have killed themselves if they had the opportunity? Of course not. Only humans even understand the principle of greed.\nYet as you will observe more and more of it will be happening and every bit will be one step better to actually getting the results we are pursuing as a society. It is going to take decades for us to get there however that is still better than the alternative. There is no reason to continue depending just on non-Renewable Energy when we do not have to.\nGarbage. Do not believe it. It's just propaganda. For just $200, you can assemble and install working wind and planetary systems for your house. No expensive specialists, made complex blueprints, or outrageously pricey parts. Proven do-it-yourself techniques are being commonly applied throughout the nation.\nYou will require to do your research study about the different types of renewable resource to utilize. Lots of individuals are benefiting from solar energy and even some are capturing onto wind power. Do some research study and identify which source will work best for you.\nCoal is formed through the dead remains of trees, ferns and other plants that lived 300 to 400 million years ago. Swamps would form, which would be covered by the sea. The sea itself consists of a large amount of sulphur, which winds up in the coal when the water receded. If sulphur isn't gotten rid of first, it is released when coal is burned, although it does depend upon where exactly the coal originates from.\nAfter all, if they desire live far from the power grid, they will have to invest at least twenty thousand dollars on the PV power setup, depending upon the size of their house. And oftentimes, they can just see a full return on their financial investment after 20 years. This is method too long.\nThe reality is, our non-renewable resources are disappearing quick. We each can start to make a difference by merely taking a look at solar energy and wind energy as an alternative source of power. It's excellent for the earth and your pocket. Make power at house with solar and wind\nhere energy to eliminate your power bill. Get our complete guide now.\nSolar Power Packages For Home - Create Electrical Power And Save Money\nSustainable energy is our only possibility. That might sound severe, however it's the fact. If we continue to depend on oil and other present types of energy production, there will be serious consequences. While there are lots of reasons for our gashouse emission problems, oil is the number one culprit. And why do we continue to utilize oil? Revenues. If we don't alter, our own greed will cause our death. That's fantastic to think about. The dinosaurs were supposedly extinct by a meteor; they had no chance. Do you think they would have killed themselves if they had the opportunity? Of course not. Only humans even understand the principle of greed.",
    "highlightText": "",
    "highlightTitle": "",
    "highlightThreadTitle": "",
    "language": "english",
    "sentiment": "positive",
    "categories": [
        "Science and Technology",
        "Environment",
        "Economy, Business and Finance"
    ],
    "external_links": [
        "https://www.iea.org/energy-system/renewables",
        "https://iea.org/energy-system/renewables"
    ],
    "external_images": [],
    "entities": {
        "persons": [],
        "organizations": [
            {
                "name": "solar power packages for home - create electrical power",
                "sentiment": "negative"
            }
        ],
        "locations": []
    },
    "rating": null,
    "crawled": "2023-12-29T03:24:36.042+02:00",
    "updated": "2023-12-29T03:24:36.042+02:00"
}