{
    "thread": {
        "uuid": "8959f585a91e5eaecf9b7e0d448b0ba5080fe091",
        "url": "https://mx.advfn.com/bolsa-de-valores/COIN/ADAUSD/crypto-news/92906160/binance-2023-report-reveals-40-million-new-users",
        "site_full": "mx.advfn.com",
        "site": "advfn.com",
        "site_section": "https://mx.advfn.com/p.php?pid=news",
        "site_categories": [],
        "section_title": "ADVFN - Noticias",
        "title": "Binance 2023 Report Reveals: 40 Million New Users Added, Total Registered Users Reach 170 Million",
        "title_full": "Binance 2023 Report Reveals: 40 Million New Users Added, Total Registered Users Reach 170 Million",
        "published": "2023-12-28T20:30:00.000+02:00",
        "replies_count": 0,
        "participants_count": 1,
        "site_type": "news",
        "country": "GB",
        "main_image": "https://mx.advfn.com/p.php?pid=staticchart&amp;s=COIN:ADAUSD&amp;p=5&amp;t=52",
        "performance_score": 0,
        "domain_rank": 8791,
        "domain_rank_updated": "2023-12-26T12:06:20.000+02:00",
        "reach": null,
        "social": {
            "facebook": {
                "likes": 0,
                "comments": 0,
                "shares": 0
            },
            "gplus": {
                "shares": 0
            },
            "pinterest": {
                "shares": 0
            },
            "linkedin": {
                "shares": 0
            },
            "stumbledupon": {
                "shares": 0
            },
            "vk": {
                "shares": 0
            }
        }
    },
    "uuid": "8959f585a91e5eaecf9b7e0d448b0ba5080fe091",
    "url": "https://mx.advfn.com/bolsa-de-valores/COIN/ADAUSD/crypto-news/92906160/binance-2023-report-reveals-40-million-new-users",
    "ord_in_thread": 0,
    "parent_url": null,
    "author": "NEWSBTC",
    "published": "2023-12-28T20:30:00.000+02:00",
    "title": "Binance 2023 Report Reveals: 40 Million New Users Added, Total Registered Users Reach 170 Million",
    "text": "In its recently released 2023 review report, Binance, the world’s leading cryptocurrency exchange, showcased significant growth despite facing legal disputes and regulatory scrutiny. The report highlighted the evolving crypto market, increasing institutional interest, and the company’s commitment to compliance and user experience. Binance’s 2023 Review Despite a volatile year for the market, Binance emphasized that digital asset regulation had taken a direction toward greater clarity and harmonization in some regions. The exchange acknowledged the challenges but noted that Web3 adoption and institutional interest continued to grow steadily, demonstrating the industry’s resilience and long-term potential. Regarding growth within the company, Binance Square, formerly known as Binance Feed, was introduced as a social platform designed to be the central hub for Web3 content. According to the report, the platform experienced substantial growth, expanding from 1,200 to 11,000 creators and attracting over 1.6 million active daily users. Binance Square aimed to facilitate conversations and enable users to generate “compelling content,” fostering engagement within the Web3 community. Related Reading: Axie Infinity Springs Back To Life With Surprise 35% Rally – Details In October, Binance Futures launched its Copy Trading feature, allowing users to replicate the trading strategies of expert lead traders. This feature provided a monetization avenue for trading experts and added a social aspect to the trading experience of the platform users. Furthermore, Binance continued its support of fiat currencies, reaching 69 supported fiat currencies with 30 fiat channels available globally. Binance P2P, the peer-to-peer trading platform, expanded the number of supported payment methods to 970 and fiat currencies to 112. The report highlights that the platform facilitated 18% more trades with 39% more users than the previous year. The report further noted Binance’s commitment to compliance, with a significant investment of $213 million in its compliance program, a 35% increase from the previous year. Binance allocated substantial resources to develop in-house compliance tools, including a case management system and an internal transaction monitoring engine. Is Binance Leading The Way In Crypto Venture Funding? Per the report, in 2023, Binance focused on enhancing user experience by partnering with localized KYC (know-your-customer) vendors and implementing various electronic ID (eID) solutions globally. The exchange added support for 298 new ID and proof-of-address documents across 64 countries, streamlining the onboarding process for users. To make Web3 “more accessible,” the report notes that Binance launched its Web3 Wallet, which aims to provide a “secure” gateway into the world of decentralized finance (DeFi). The platform aimed to address usability barriers and attract new users by offering improved product and user experience across DeFi, blockchain gaming, and SocialFi. Ultimately, while the crypto venture funding market faced challenges in 2023, Binance Labs emerged as one of the most active participants in the crypto venture capital (VC) space, particularly in the DeFi and Web3 gaming sectors, according to the exchange. Related Reading: Crypto Analyst Predicts Major Price Shift For Cardano (ADA) Overall, Binance’s 2023 Review Report highlights the company’s focus on compliance, user experience, and expanding Web3 offerings as key to continued growth despite ongoing legal issues and regulatory enforcement actions. As of the current update, Binance Coin (BNB) demonstrates a significant upward trend in price action, surging to $330. This surge represents a 21% increase over the past seven days. Featured image from Shutterstock, chart from TradingView.com",
    "highlightText": "",
    "highlightTitle": "",
    "highlightThreadTitle": "",
    "language": "english",
    "sentiment": "positive",
    "categories": [
        "Economy, Business and Finance",
        "Science and Technology"
    ],
    "external_links": [],
    "external_images": [],
    "entities": {
        "persons": [
            {
                "name": "binance",
                "sentiment": "none"
            }
        ],
        "organizations": [],
        "locations": [
            {
                "name": "binance",
                "sentiment": "none"
            },
            {
                "name": "binance square",
                "sentiment": "none"
            }
        ]
    },
    "rating": null,
    "crawled": "2023-12-29T02:42:18.375+02:00",
    "updated": "2023-12-29T02:42:18.375+02:00"
}